lib_calc_manu/__init__.py
lib_calc_manu/operacoes.py
calculadora_manuesy_api-0.1.2.dist-info/METADATA
calculadora_manuesy_api-0.1.2.dist-info/WHEEL
calculadora_manuesy_api-0.1.2.dist-info/top_level.txt
calculadora_manuesy_api-0.1.2.dist-info/RECORD
