Metadata-Version: 2.4
Name: calculadora-manuesy-api
Version: 0.1.2
Summary: Uma calculadora básica com FastAPI
Author: Manuely Lemos
Author-email: manumeireleslemos@gmail.com
Classifier: Programming Language :: Python :: 3
Classifier: License :: OSI Approved :: MIT License
Requires-Python: >=3.7
Requires-Dist: fastapi
Requires-Dist: uvicorn
Requires-Dist: pydantic
Dynamic: author
Dynamic: author-email
Dynamic: classifier
Dynamic: description
Dynamic: description-content-type
Dynamic: requires-dist
Dynamic: requires-python
Dynamic: summary
